edunet/core/applications/application.py
edunet/core/applications/simple_http_application.py
edunet/core/networking/handlers/connection_handler.py
edunet/core/networking/handlers/simple_http_connection_handler.py
edunet/core/networking/handlers/wsgi_handler.py
edunet/core/networking/listeners/listener.py
edunet/core/networking/listeners/tcp_listener.py
edunet/core/nodes/node.py
edunet/core/nodes/simple_http_node.py
edunet/exceptions.py
edunet/models/base_types.py
edunet/models/http.py
edunet/validators/http_validators.py
edunet-0.2.4.dist-info/LICENSE
edunet-0.2.4.dist-info/METADATA
edunet-0.2.4.dist-info/WHEEL
edunet-0.2.4.dist-info/RECORD
