Metadata-Version: 2.1
Name: edunet
Version: 0.2.4
Summary: Simple Network Simulation For The Funs!
Author: Wajdi Al-Hawari
Author-email: w.hawari@gmail.com
Requires-Python: >=3.9,<4.0
Classifier: Programming Language :: Python :: 3
Classifier: Programming Language :: Python :: 3.9
Classifier: Programming Language :: Python :: 3.10
Classifier: Programming Language :: Python :: 3.11
Classifier: Programming Language :: Python :: 3.12
Classifier: Programming Language :: Python :: 3.13
